socketengine/__init__.py
socketengine/client.py
socketengine/common.py
socketengine/constants.py
socketengine/host.py
socketengine/hub.py
socketengine/test.py
socketengine/transport.py
tests/__init__.py
tests/host_client_test.py
tests/hub_test.py
tests/hub_video.py
tests/test.py
tests/tmp.py
socket.engine-1.0.0.dist-info/LICENSE
socket.engine-1.0.0.dist-info/METADATA
socket.engine-1.0.0.dist-info/WHEEL
socket.engine-1.0.0.dist-info/top_level.txt
socket.engine-1.0.0.dist-info/RECORD
