Metadata-Version: 2.1
Name: socket.engine
Version: 1.0.0
Summary: A universal communication engine
Home-page: https://github.com/0xJeremy/socket.engine
Author: Jeremy Kanovsky
Author-email: kanovsky.jeremy@gmail.com
License: UNKNOWN
Platform: UNKNOWN
Classifier: Programming Language :: Python :: 3
Classifier: License :: OSI Approved :: MIT License
